{
  "db_name": "PostgreSQL",
  "query": "\n            SELECT input_price_per_token, output_price_per_token, valid_from\n            FROM model_tariffs\n            WHERE deployed_model_id = $1\n              AND api_key_purpose = $2\n              AND valid_until IS NULL\n            LIMIT 1\n            ",
  "describe": {
    "columns": [
      {
        "ordinal": 0,
        "name": "input_price_per_token",
        "type_info": "Numeric"
      },
      {
        "ordinal": 1,
        "name": "output_price_per_token",
        "type_info": "Numeric"
      },
      {
        "ordinal": 2,
        "name": "valid_from",
        "type_info": "Timestamptz"
      }
    ],
    "parameters": {
      "Left": [
        "Uuid",
        "Text"
      ]
    },
    "nullable": [
      false,
      false,
      false
    ]
  },
  "hash": "ea51a2dad7da96da8f5842939b78ed0f4240be9679f2ff8e058cc02738463ee8"
}
