{
  "db_name": "PostgreSQL",
  "query": "\n            SELECT DISTINCT\n                ak.id as \"id!\",\n                ak.name as \"name!\",\n                ak.description,\n                ak.secret as \"secret!\",\n                ak.purpose as \"purpose!\",\n                ak.user_id as \"user_id!\",\n                ak.created_at as \"created_at!\",\n                ak.last_used,\n                ak.requests_per_second,\n                ak.burst_size,\n                ak.hidden as \"hidden!\"\n            FROM api_keys ak\n            WHERE ak.user_id = $2  -- System user has access to all deployments\n\n            UNION\n\n            SELECT DISTINCT\n                ak.id as \"id!\",\n                ak.name as \"name!\",\n                ak.description,\n                ak.secret as \"secret!\",\n                ak.purpose as \"purpose!\",\n                ak.user_id as \"user_id!\",\n                ak.created_at as \"created_at!\",\n                ak.last_used,\n                ak.requests_per_second,\n                ak.burst_size,\n                ak.hidden as \"hidden!\"\n            FROM api_keys ak\n            INNER JOIN user_groups ug ON ak.user_id = ug.user_id\n            INNER JOIN deployment_groups dg ON ug.group_id = dg.group_id\n            INNER JOIN deployed_models dm ON dg.deployment_id = dm.id\n            WHERE dg.deployment_id = $1\n            AND (\n                ak.user_id = $2  -- System user always has access\n                OR (\n                    -- User has positive balance (checkpoint + delta calculation)\n                    SELECT COALESCE(\n                        (SELECT c.balance FROM user_balance_checkpoints c WHERE c.user_id = ak.user_id),\n                        0\n                    ) + COALESCE(\n                        (SELECT SUM(\n                            CASE WHEN ct.transaction_type IN ('purchase', 'admin_grant')\n                            THEN ct.amount ELSE -ct.amount END\n                        )\n                        FROM credits_transactions ct\n                        LEFT JOIN user_balance_checkpoints c ON c.user_id = ak.user_id\n                        WHERE ct.user_id = ak.user_id\n                        AND (c.checkpoint_time IS NULL OR ct.created_at > c.checkpoint_time)\n                        ),\n                        0\n                    )\n                ) > 0\n                OR (\n                    -- Free models are accessible to all users (zero balance OK)\n                    -- A model is free if it has no active tariffs or all active tariffs are zero-priced\n                    NOT EXISTS (\n                        SELECT 1 FROM model_tariffs mt\n                        WHERE mt.deployed_model_id = dm.id\n                        AND mt.valid_until IS NULL\n                        AND (mt.input_price_per_token > 0 OR mt.output_price_per_token > 0)\n                    )\n                )\n            )\n\n            UNION\n\n            SELECT DISTINCT\n                ak.id as \"id!\",\n                ak.name as \"name!\",\n                ak.description,\n                ak.secret as \"secret!\",\n                ak.purpose as \"purpose!\",\n                ak.user_id as \"user_id!\",\n                ak.created_at as \"created_at!\",\n                ak.last_used,\n                ak.requests_per_second,\n                ak.burst_size,\n                ak.hidden as \"hidden!\"\n            FROM api_keys ak\n            INNER JOIN deployment_groups dg ON dg.group_id = '00000000-0000-0000-0000-000000000000'\n            INNER JOIN deployed_models dm ON dg.deployment_id = dm.id\n            WHERE dg.deployment_id = $1\n            AND ak.user_id != '00000000-0000-0000-0000-000000000000'  -- Exclude system user (already covered above)\n            AND (\n                ak.user_id = $2  -- System user always has access\n                OR (\n                    -- User has positive balance (checkpoint + delta calculation)\n                    SELECT COALESCE(\n                        (SELECT c.balance FROM user_balance_checkpoints c WHERE c.user_id = ak.user_id),\n                        0\n                    ) + COALESCE(\n                        (SELECT SUM(\n                            CASE WHEN ct.transaction_type IN ('purchase', 'admin_grant')\n                            THEN ct.amount ELSE -ct.amount END\n                        )\n                        FROM credits_transactions ct\n                        LEFT JOIN user_balance_checkpoints c ON c.user_id = ak.user_id\n                        WHERE ct.user_id = ak.user_id\n                        AND (c.checkpoint_time IS NULL OR ct.created_at > c.checkpoint_time)\n                        ),\n                        0\n                    )\n                ) > 0\n                OR (\n                    -- Free models are accessible to all users (zero balance OK)\n                    -- A model is free if it has no active tariffs or all active tariffs are zero-priced\n                    NOT EXISTS (\n                        SELECT 1 FROM model_tariffs mt\n                        WHERE mt.deployed_model_id = dm.id\n                        AND mt.valid_until IS NULL\n                        AND (mt.input_price_per_token > 0 OR mt.output_price_per_token > 0)\n                    )\n                )\n            )\n            ",
  "describe": {
    "columns": [
      {
        "ordinal": 0,
        "name": "id!",
        "type_info": "Uuid"
      },
      {
        "ordinal": 1,
        "name": "name!",
        "type_info": "Varchar"
      },
      {
        "ordinal": 2,
        "name": "description",
        "type_info": "Text"
      },
      {
        "ordinal": 3,
        "name": "secret!",
        "type_info": "Varchar"
      },
      {
        "ordinal": 4,
        "name": "purpose!",
        "type_info": "Varchar"
      },
      {
        "ordinal": 5,
        "name": "user_id!",
        "type_info": "Uuid"
      },
      {
        "ordinal": 6,
        "name": "created_at!",
        "type_info": "Timestamptz"
      },
      {
        "ordinal": 7,
        "name": "last_used",
        "type_info": "Timestamptz"
      },
      {
        "ordinal": 8,
        "name": "requests_per_second",
        "type_info": "Float4"
      },
      {
        "ordinal": 9,
        "name": "burst_size",
        "type_info": "Int4"
      },
      {
        "ordinal": 10,
        "name": "hidden!",
        "type_info": "Bool"
      }
    ],
    "parameters": {
      "Left": [
        "Uuid",
        "Uuid"
      ]
    },
    "nullable": [
      null,
      null,
      null,
      null,
      null,
      null,
      null,
      null,
      null,
      null,
      null
    ]
  },
  "hash": "e4b2e00ea10cd8fcfecf0fd51ec1a81bc0ee620d4ba9a472619c41f60dfa9a74"
}
