{
  "db_name": "PostgreSQL",
  "query": "\n            SELECT u.id, u.email, u.username, u.display_name,\n                   u.low_balance_threshold as \"low_balance_threshold!: rust_decimal::Decimal\",\n                   u.low_balance_notification_sent\n            FROM users u\n            WHERE u.id != '00000000-0000-0000-0000-000000000000'\n              AND u.is_deleted = false\n              AND u.low_balance_threshold IS NOT NULL\n            ",
  "describe": {
    "columns": [
      {
        "ordinal": 0,
        "name": "id",
        "type_info": "Uuid"
      },
      {
        "ordinal": 1,
        "name": "email",
        "type_info": "Varchar"
      },
      {
        "ordinal": 2,
        "name": "username",
        "type_info": "Varchar"
      },
      {
        "ordinal": 3,
        "name": "display_name",
        "type_info": "Varchar"
      },
      {
        "ordinal": 4,
        "name": "low_balance_threshold!: rust_decimal::Decimal",
        "type_info": "Float4"
      },
      {
        "ordinal": 5,
        "name": "low_balance_notification_sent",
        "type_info": "Bool"
      }
    ],
    "parameters": {
      "Left": []
    },
    "nullable": [
      false,
      false,
      false,
      true,
      true,
      false
    ]
  },
  "hash": "f67f7d14822070c258bf12dd0a2d68eecf847b9288a74e3244587ac0c8a2861c"
}
